ribfind/__init__.py
ribfind/cli.py
ribfind/cluster.py
ribfind/contact.py
ribfind/dssp.py
ribfind/graph.py
ribfind/interaction.py
ribfind/model.py
ribfind/rnamlparse.py
ribfind/structures.py
ribfind/writers.py
ribfind/template/chimerax.txt
ribfind/template/rigid_body.txt
ribfind/template/summary.txt
ribfind-2.2.0.dist-info/COPYING.txt
ribfind-2.2.0.dist-info/METADATA
ribfind-2.2.0.dist-info/WHEEL
ribfind-2.2.0.dist-info/entry_points.txt
ribfind-2.2.0.dist-info/top_level.txt
ribfind-2.2.0.dist-info/RECORD
